[1,["20g1ukYUVPvKWKBRznAKo+@f9941","f1KiPEuSRDIqJgPZgkKPHo@f9941","1brw/JvvpFnIvdrxpFCgMZ","dcyIbtzn5AurPQ3vm3LS4n","12Y9dMgWdJKJGmTiZyQR9H@a804a","54TknWPwVPqJqeCR+Y/Czo@f9941","95EkngnxZFbYuFpsqVTaFr@f9941","45go8ltQ1MUqWR4ZSRpiuM@f9941","2c1tmJ8rZHBZx38MD0Uv0o","07I8Di42hCfIhVnRkyJT22","146FhxQfZDOajGGjFFBRAo","4avwMVrk9MeanE609quXAr","3cFPKP+xVFc6CPA3IHsQsg","b6VGlG/+5E+4yTwQIlFKdI","9dJ65vhRxBf61NVz842++t","12Y9dMgWdJKJGmTiZyQR9H@2e76e","12Y9dMgWdJKJGmTiZyQR9H@8abdc"],["node","_spriteFrame","_target","_mesh","_normalSprite","_effectAsset","target","_checkMark","root","asset","_hoverSprite","_pressedSprite","_disabledSprite","_parent","_cameraComponent","targetNode","mhModel","mpModel","scene","boxPrefab","spherePrefab","mpDebug","mhDebug","mp","mh"],[["cc.Node",["_name","_id","_layer","_active","_objFlags","__editorExtras__","_parent","_components","_lpos","_children","_lscale","_lrot","_euler","_prefab"],-3,1,9,5,2,5,5,5,4],["cc.Widget",["_alignFlags","_top","_isAbsTop","_alignMode","_isAbsLeft","_left","_right","_isAbsRight","node"],-5,1],["cc.Sprite",["_sizeMode","_type","_name","node","_spriteFrame"],0,1,6],["cc.UITransform",["_name","node","_contentSize"],2,1,5],["cc.MeshRenderer",["_name","node","_materials","bakeSettings","_mesh","__prefab"],2,1,3,4,6,4],["cc.Node",["_name","_layer","_active","_parent","_components"],0,1,12],["cc.Node",["_name","_layer","_parent","_components","_lscale","_lpos"],1,1,2,5,5],["cc.BoxCollider",["_name","node","_center","_size"],2,1,5,5],["cc.ClickEvent",["_componentId","handler","customEventData","target"],0,1],["cc.Toggle",["_isChecked","node","_normalColor","_target","checkEvents","_checkMark","_normalSprite"],2,1,5,1,9,1,6],["cc.Camera",["_visibility","_name","_projection","_priority","_orthoHeight","_far","_clearFlags","node","_color"],-4,1,5],["cc.Material",["_name","_techIdx","_states","_defines","_props"],-1,12],["cc.SceneAsset",["_name"],2],["cc.Scene",["_name","_children","_prefab","_globals"],2,12,4,4],["cc.PrefabInfo",["root","asset","instance","targetOverrides","nestedPrefabInstanceRoots"],-1,2],["cc.PrefabInfo",["fileId","targetOverrides","nestedPrefabInstanceRoots","root","instance","asset"],0,1,4,6],["cc.SceneGlobals",["ambient","shadows","_skybox","fog","octree","skin","lightProbeInfo"],3,4,4,4,4,4,4,4],["cc.AmbientInfo",["_skyIllumHDR","_skyIllumLDR","_skyColorHDR","_groundAlbedoHDR","_skyColorLDR","_groundAlbedoLDR"],1,5,5,5,5],["cc.ShadowsInfo",["_size"],3,5],["cc.SkyboxInfo",[],3],["cc.FogInfo",["_fogColor"],3,5],["cc.OctreeInfo",[],3],["cc.SkinInfo",["_enabled","_sssIntensity"],1],["cc.LightProbeInfo",[],3],["cc.PlaneCollider",["_enabled","node"],2,1],["9a884xRq8hErahsBz05l4NK",["moveSpeed","moveSpeedShiftScale","node"],1,1],["cc.SphereCollider",["_isTrigger","_radius","node"],1,1],["cc.RigidBody",["_type","node"],2,1],["cc.Canvas",["_name","node","_cameraComponent"],2,1,1],["858203AB+NG5aVJJY57I+2I",["_name","node","targetNode"],2,1,1],["cc.ToggleContainer",["_name","node"],2,1],["cc.Button",["_transition","node","clickEvents","_normalColor","_target","_normalSprite","_hoverSprite","_pressedSprite","_disabledSprite"],2,1,9,5,1,6,6,6,6],["44707WHM/dLRr3ZRoRjlPbE",["_name","boxAmount","sphereAmount","node","gravity","boxPrefab","spherePrefab"],0,1,5,6,6],["cb265jDI35FZ6rJG5oiHVsY",["_name","node","roleNode","planeNode"],2,1,1,1],["83969PIqqtCzpmwWOBT+ujw",["_enabled","moveSpeed","moveSpeedShiftScale","node"],0,1],["cc.ModelBakeSettings",[],3],["cc.PrefabInstance",["fileId","prefabRootNode","propertyOverrides"],1,9],["CCPropertyOverrideInfo",["propertyPath","targetInfo","value"],2,4,4],["CCPropertyOverrideInfo",["value","propertyPath","targetInfo"],1,4],["CCPropertyOverrideInfo",["propertyPath","targetInfo","value"],2,4,8],["cc.TargetInfo",["localID"],2],["cc.Label",["_string","_actualFontSize","_fontSize","_enableWrapText","_underlineHeight","node","_color"],-2,1,5],["637b9lEDVZHg4+RBMRx6Nbc",["node","mpModel","mhModel","mpDebug","mhDebug","mp","mh"],3,1,1,1,6,6,6,6],["cc.DirectionalLight",["_shadowBias","_shadowSaturation","_shadowDistance","_csmLevel","_shadowNear","_shadowFar","node","_color","_staticSettings"],-3,1,5,4],["cc.StaticLightSettings",[],3],["cc.CompPrefabInfo",["fileId"],2]],[[40,0,2],[38,0,1,2,3],[3,1,2,1],[35,1],[0,0,2,6,9,7,8,3],[11,0,1,2,3,4,5],[7,0,1,2],[3,0,1,2,2],[8,0,1,3,3],[4,0,1,2,3,4,2],[39,0,1,2,2],[0,4,5,6,13,3],[15,0,1,2,3,4,5,4],[2,1,0,3,4,3],[2,0,3,4,2],[31,0,1,2,3,4,5,6,7,8,2],[8,0,1,2,3,4],[36,0,1,2,3],[0,0,1,6,7,3],[0,0,6,7,8,10,2],[0,0,6,7,8,11,10,12,2],[0,0,2,6,7,3],[5,0,2,1,3,4,4],[6,0,2,3,4,2],[26,0,1,2,3],[1,0,1,4,2,3,8,6],[2,2,0,3,3],[9,0,1,2,3,4,5,6,2],[37,0,1,2,2],[41,0,1,2,3,4,5,6,6],[12,0,2],[13,0,1,2,3,2],[0,0,1,6,8,10,3],[0,0,1,6,9,7,10,3],[0,0,1,6,9,7,3],[0,0,2,1,6,9,7,8,4],[0,0,2,6,9,7,8,10,3],[0,0,2,6,9,7,3],[0,0,2,6,7,8,3],[0,0,6,7,8,11,12,2],[0,0,3,1,6,9,4],[0,0,1,6,7,8,11,12,3],[5,0,1,3,4,3],[6,0,1,2,3,5,3],[14,0,1,2,3,4,5],[16,0,1,2,3,4,5,6,1],[17,0,1,2,3,4,5,3],[18,0,1],[19,1],[20,0,1],[21,1],[22,0,1,3],[23,1],[7,0,1,2,3,2],[24,0,1,2],[25,0,1,2,3],[27,0,1,2],[3,1,1],[28,0,1,2,2],[1,0,8,2],[1,0,5,6,1,4,2,3,8,8],[1,0,5,1,4,2,3,8,7],[1,0,6,1,7,2,3,8,7],[29,0,1,2,2],[30,0,1,2],[2,0,3,2],[9,1,2,3,4,5,6,1],[32,0,1,2,3,4,5,6,4],[33,0,1,2,3,2],[10,1,0,7,8,3],[10,2,3,4,5,6,0,7,8,7],[34,0,1,2,3,4],[4,0,1,5,2,3,2],[4,0,1,2,3,2],[42,0,1,2,3,4,5,6,1],[43,0,1,2,3,4,5,6,7,8,7],[44,1],[45,0,2]],[[[[5,"mp","0",[{"priority":127,"rasterizerState":{},"depthStencilState":{"stencilTestFront":true,"stencilFuncFront":5,"stencilFailOpFront":0,"stencilFailOpBack":0},"blendState":{"targets":[{}]}},{},{},{}],[{},{},{},{}],[[[{"roughness":0.8,"metallic":0.6},"mainColor",8,[4,4293356435],"emissive",8,[4,4282862151]],{},{},{}],11,0,0,0]]],0,0,[0],[5],[2]],[[[5,"mp-debug","1",[{"priority":127,"blendState":{"targets":[{}]},"depthStencilState":{"stencilFailOpBack":0,"stencilFailOpFront":0},"rasterizerState":{}}],[{"OCCLUSION_CHANNEL":"b","ROUGHNESS_CHANNEL":"r","METALLIC_CHANNEL":"g"}],[[[{"occlusion":0,"roughness":0.8,"metallic":0.6},"emissive",8,[4,4285561204],"mainColor",8,[4,2104488376]]],11]]],0,0,[0],[5],[2]],[[[5,"mh","0",[{"priority":125,"blendState":{"targets":[{}]},"depthStencilState":{"depthFunc":7,"depthWrite":false,"stencilFailOpFront":2,"stencilPassOpFront":2,"stencilTestFront":true,"stencilZFailOpFront":2},"rasterizerState":{}}],[{"OCCLUSION_CHANNEL":"b","ROUGHNESS_CHANNEL":"r","METALLIC_CHANNEL":"g"}],[[[{"occlusion":0,"roughness":0.8,"metallic":0.6},"mainColor",8,[4,4278190080]]],11]]],0,0,[0],[5],[2]],[[[30,"demo-simple-hole"],[31,"demo-simple-hole",[[-4,[32,"LT","c0HltZYy1N/6GJ2QgTkEFV",-5,[1,-18,0,17],[1,1,1,10]],-6,-7,-8,-9,-10,-11,-12],1,4,1,1,1,1,1,1,1],[44,null,null,null,null,[-1,-2,-3]],[45,[46,2000,0.078125,[2,0.7725490196078432,0.6862745098039216,0.2901960784313725,0.0520833125],[2,0.9411764705882353,0.7568627450980392,0.19215686274509802,1],[2,0.7725490196078432,0.6862745098039216,0.2901960784313725,0.520833125],[2,0.9411764705882353,0.7568627450980392,0.19215686274509802,1]],[47,[0,512,512]],[48],[49,[4,4292993505]],[50],[51,false,5],[52]]],[33,"Plane","463CuTi+NHuLidk1UWR8iz",1,[-15,-16,-17,-18,-19],[[53,"Plane<BoxCollider>",-13,[1,0,-4.99,0],[1,10,10,10]],[54,false,-14]],[1,4,4,4]],[34,"Role","6fR2gkQblM96am9gGBwXzi",1,[-24,-25],[[55,0.1,2,-20],[24,true,2,-21],[24,true,2.5,-22],[56,4,-23]]],[35,"Canvas",16384,"09LjbIGX5D4a3mNHSMTvKJ",1,[-30,-31,-32,-33],[[7,"Canvas<UITransform>",-26,[5,960,640]],[58,"Canvas<Canvas>",-28,-27],[59,45,-29]],[1,480,320,0]],[36,"Debug",16384,4,[-38,-39],[[63,"Debug<active-change>",-35,-34],[57,-36],[60,9,0.07,430,0.22,false,false,1,-37]],[1,-372.8,139.2,0],[1,0.8,0.8,0.8]],[4,"ToggleGroup",16384,4,[-43,-44,-45],[[7,"ToggleGroup<UITransform>",-40,[5,0,0]],[64,"ToggleGroup<ToggleContainer>",-41],[61,9,0.15,0.19395156250000004,false,false,1,-42]],[1,-336,195.87099999999998,0]],[4,"Debug-Material",16384,5,[-52],[[2,-46,[5,150,40]],[13,1,0,-47,21],[15,2,-50,[[8,"637b9lEDVZHg4+RBMRx6Nbc","enable",-49]],[4,4292269782],-48,26,27,28,29],[25,8,0.3,false,false,1,-51]],[1,25,0,0]],[4,"Debug-Camera",16384,5,[-59],[[2,-53,[5,150,40]],[13,1,0,-54,30],[15,2,-57,[[8,"83969PIqqtCzpmwWOBT+ujw","changeEnable",-56],[8,"9a884xRq8hErahsBz05l4NK","changeEnable",3]],[4,4292269782],-55,31,32,33,34],[25,9,1,false,false,1,-58]],[1,25,-70,0]],[4,"Toggle1",16384,6,[-66],[[2,-60,[5,32,32]],[14,0,-61,11],[66,-65,[4,4292269782],-64,[[16,"44707WHM/dLRr3ZRoRjlPbE","toggleAlgorithms","0",-63]],-62,12]],[1,-62,0,0]],[18,"Setup","79T0zbSZNLEZQ8MhOoDNif",1,[[67,"Instantiate<Instantiate>",25,26,-67,[1,0,-80,0],13,14],[68,"Setup<EntitySetup>",-68,3,2]]],[37,"Toggle2",16384,6,[-74],[[2,-69,[5,32,32]],[14,0,-70,16],[27,false,-73,[4,4292269782],-72,[[16,"44707WHM/dLRr3ZRoRjlPbE","toggleAlgorithms","1",10]],-71,17]]],[4,"Toggle3",16384,6,[-80],[[2,-75,[5,32,32]],[14,0,-76,18],[27,false,-79,[4,4292269782],-78,[[16,"44707WHM/dLRr3ZRoRjlPbE","toggleAlgorithms","2",10]],-77,19]],[1,62,0,0]],[38,"Debug-Toggle",16384,4,[[2,-81,[5,20,20]],[13,1,0,-82,20],[15,2,-84,[[8,"858203AB+NG5aVJJY57I+2I","changeActive",5]],[4,4292269782],-83,35,36,37,38],[62,33,0.7160104166666666,0.17999843749999994,false,false,1,-85]],[1,-217.37,194.80100000000004,0]],[39,"Camera",3,[[69,"Camera<Camera>",1082654720,-86,[4,4281808951]],[71,false,0.15,2,-87]],[1,0,47.50862037979112,21.978974084149883],[3,-0.5385677685561009,-0.0027812767367955283,-0.0017777701760375887,0.8425757311395912],[1,-65.17278658812455,-0.37825642018224326,-7.951386703658792e-15]],[19,"Z+",2,[[9,"Cube<MeshRenderer>",-88,[0],[3],1],[6,"Z+<BoxCollider>",-89]],[1,0,0.24,5],[1,10,0.5,0.5]],[20,"X+",2,[[9,"Cube<MeshRenderer>",-90,[2],[3],3],[6,"X+<BoxCollider>",-91]],[1,5,0.24,0],[3,0,0.7071067811865475,0,0.7071067811865476],[1,10.5,0.5,0.5],[1,0,90,0]],[20,"X-",2,[[9,"Cube<MeshRenderer>",-92,[4],[3],5],[6,"X-<BoxCollider>",-93]],[1,-5,0.24,0],[3,0,0.7071067811865475,0,0.7071067811865476],[1,10.5,0.5,0.5],[1,0,90,0]],[19,"Z-",2,[[9,"Cube<MeshRenderer>",-94,[6],[3],7],[6,"Z-<BoxCollider>",-95]],[1,0,0.24,-5],[1,10,0.5,0.5]],[40,"EditNode",false,"38vHLnAlpEjoEMZWUL+p/9",1,[-96,-97]],[11,0,{},19,[12,"daf5pA+WdOjJ3Q1V9SCs6I",null,null,-98,[17,"b1tPaAxoJILZoUYM99v1HS",null,[[28,["lightmapSettings"],[0,["dbe9qPYo9CTYCm19pYojGJ"]],[3]],[1,1,["_shadowReceivingMode"],[0,["dbe9qPYo9CTYCm19pYojGJ"]]],[1,1,["_group"],[0,["5fXJILxcRPs7NJH/K5fUB3"]]],[1,1,["_type"],[0,["5fXJILxcRPs7NJH/K5fUB3"]]]]],9]],[11,0,{},19,[12,"154raAV3lGI6TRnk96VGKr",null,null,-99,[17,"ebO2qgRrhNk6nnVV64LPWe",null,[[28,["lightmapSettings"],[0,["91ekQCCelIT6iV6goe26vQ"]],[3]],[1,1,["_shadowReceivingMode"],[0,["91ekQCCelIT6iV6goe26vQ"]]],[1,1,["_group"],[0,["24ZFz2nX9Lt50DXUzdXdi/"]]],[1,1,["_type"],[0,["24ZFz2nX9Lt50DXUzdXdi/"]]]]],10]],[42,"Checkmark",16384,9,[[[2,-100,[5,32,32]],-101],4,1]],[22,"Checkmark",false,16384,11,[[[7,"Checkmark<UITransform>",-102,[5,32,32]],-103],4,1]],[22,"Checkmark",false,16384,12,[[[7,"Checkmark<UITransform>",-104,[5,32,32]],-105],4,1]],[21,"Label",16384,7,[[2,-106,[5,136.73,50.4]],[29,"Debug-Material",20,20,false,0,-107,[4,4278190080]]]],[18,"Debug","51RnH/KJhLKL63tSZX+4S/",1,[[74,-110,-109,-108,22,23,24,25]]],[21,"Label",16384,8,[[2,-111,[5,136.73,50.4]],[29,"Debug-Camera",20,20,false,0,-112,[4,4278190080]]]],[11,0,{},1,[12,"57r1NJa1ZEMpiY0enYfIAb",null,null,-113,[17,"d0UP9j/wdPkoZaM+vQ5NDQ",null,[[1,0,["_visFlags"],[0,["e7FRCPtFFL6Y2InGMdTBwo"]]],[1,null,["_customMaterial"],[0,["e7FRCPtFFL6Y2InGMdTBwo"]]],[1,0,["_lockFlags"],[0,["5aIpjsnZ9IfYQU/MeZ92XO"]]],[1,0,["_visFlags"],[0,["b71vSPzDtKV78P+a2nj1N7"]]],[1,null,["_customMaterial"],[0,["b71vSPzDtKV78P+a2nj1N7"]]],[1,0,["_underlineHeight"],[0,["b71vSPzDtKV78P+a2nj1N7"]]],[10,["_contentSize"],[0,["08vaWBMJxOcbQc4M4aKHRn"]],[5,400,50.4]],[1,0,["_visFlags"],[0,["88zKtpzsBBnISFYvsqSsZO"]]],[1,null,["_customMaterial"],[0,["88zKtpzsBBnISFYvsqSsZO"]]],[1,0,["_underlineHeight"],[0,["88zKtpzsBBnISFYvsqSsZO"]]],[1,0,["_lockFlags"],[0,["3fEyK+0Z9ItJJyXZ2YUuzs"]]],[10,["_lpos"],[0,["576IQCLsZLualxUovryQb2"]],[1,0,0,1000]],[10,["_lpos"],[0,["ebL6DWAlJIbqopmwPzW/g+"]],[1,0,282,0]],[10,["_lpos"],[0,["57r1NJa1ZEMpiY0enYfIAb"]],[1,480,320,0]]]],39]],[41,"Main Light","c0y6F5f+pAvI805TdmxIjx",1,[[75,1,0.2980392156862745,100,1,1,30,-114,[4,4289111718],[76]]],[1,-6.791370541662555,13.317064976229506,5.958772396826403],[3,-0.5059618952453693,-0.20662465922817025,-0.12624349694820103,0.8278713573256287],[1,-62.862311413491,-28.02560484976864,0.0035327449484812497]],[23,"ground",2,[-115],[1,4,1,4]],[72,"Plane<ModelComponent>",30,[77,"e0uHCYkZ1D1I9glcT6oLf2"],[8],[3]],[65,0,22],[23,"Cylinder",3,[-116],[1,5,0.01,5]],[73,"Cylinder<MeshRenderer>",33,[15],[3]],[26,"Checkmark<Sprite>",0,23],[26,"Checkmark<Sprite>",0,24],[43,"UICamera_Canvas",16384,4,[-117],[1,0,0,1000]],[70,0,1073741824,320,2000,0,41959424,37,[4,0]]],0,[0,-1,20,0,-2,21,0,-3,28,0,-1,29,0,13,1,0,-3,2,0,-4,19,0,-5,4,0,-6,26,0,-7,3,0,-8,10,0,-9,28,0,0,2,0,0,2,0,-1,15,0,-2,16,0,-3,17,0,-4,18,0,-5,30,0,0,3,0,0,3,0,0,3,0,0,3,0,-1,33,0,-2,14,0,0,4,0,14,38,0,0,4,0,0,4,0,-1,6,0,-2,13,0,-3,5,0,-4,37,0,15,5,0,0,5,0,0,5,0,0,5,0,-1,7,0,-2,8,0,0,6,0,0,6,0,0,6,0,-1,9,0,-2,11,0,-3,12,0,0,7,0,0,7,0,2,7,0,6,26,0,0,7,0,0,7,0,-1,25,0,0,8,0,0,8,0,2,8,0,6,14,0,0,8,0,0,8,0,-1,27,0,0,9,0,0,9,0,7,32,0,6,10,0,2,9,0,0,9,0,-1,22,0,0,10,0,0,10,0,0,11,0,0,11,0,7,35,0,2,11,0,0,11,0,-1,23,0,0,12,0,0,12,0,7,36,0,2,12,0,0,12,0,-1,24,0,0,13,0,0,13,0,2,13,0,0,13,0,0,13,0,0,14,0,0,14,0,0,15,0,0,15,0,0,16,0,0,16,0,0,17,0,0,17,0,0,18,0,0,18,0,-1,20,0,-2,21,0,8,20,0,8,21,0,0,22,0,-2,32,0,0,23,0,-2,35,0,0,24,0,-2,36,0,0,25,0,0,25,0,16,34,0,17,31,0,0,26,0,0,27,0,0,27,0,8,28,0,0,29,0,-1,31,0,-1,34,0,-1,38,0,18,1,117],[0,0,0,0,0,0,0,0,0,0,0,0,0,0,0,0,0,0,0,0,0,0,0,0,0,0,0,0,0,0,0,0,0,0,0,0,0,0,0,0,31,32,34,35,36],[-1,3,-1,3,-1,3,-1,3,-1,9,9,1,4,19,20,-1,1,4,1,4,1,1,21,22,23,24,4,10,11,12,1,4,10,11,12,4,10,11,12,9,3,1,3,1,1],[3,4,3,4,3,4,3,4,8,9,10,1,1,10,9,11,1,1,1,1,0,0,12,13,8,11,0,0,5,6,0,0,0,5,6,0,0,5,6,14,15,7,16,7,7]],[[[5,"mh-debug","1",[{"priority":126,"blendState":{"targets":[{}]},"depthStencilState":{},"rasterizerState":{}}],[{"OCCLUSION_CHANNEL":"b","ROUGHNESS_CHANNEL":"r","METALLIC_CHANNEL":"g"}],[[[{"occlusion":0,"roughness":0.8,"metallic":0.6},"emissive",8,[4,4283776815],"mainColor",8,[4,2129503854]]],11]]],0,0,[0],[5],[2]]]]
